flake8_confusables.py
flake8_confusables-0.1.0.dist-info/DESCRIPTION.rst
flake8_confusables-0.1.0.dist-info/METADATA
flake8_confusables-0.1.0.dist-info/RECORD
flake8_confusables-0.1.0.dist-info/WHEEL
flake8_confusables-0.1.0.dist-info/entry_points.txt
flake8_confusables-0.1.0.dist-info/metadata.json
flake8_confusables-0.1.0.dist-info/top_level.txt
