Metadata-Version: 2.0
Name: flake8-confusables
Version: 0.1.0
Summary: A flake8 plugin to check for ambiguous identifiers
Home-page: https://gitlab.com/dirn/flake8-confusables
Author: Andy Dirnberger
Author-email: andy@dirnberger.me
License: MIT
Keywords: flake8,confusables,ambiguity
Platform: UNKNOWN
Classifier: Development Status :: 3 - Alpha
Classifier: Environment :: Console
Classifier: Framework :: Flake8
Classifier: Intended Audience :: Developers
Classifier: License :: OSI Approved :: MIT License
Classifier: Programming Language :: Python :: 3
Classifier: Programming Language :: Python :: 3.4
Classifier: Programming Language :: Python :: 3.5
Classifier: Programming Language :: Python :: 3.6
Classifier: Topic :: Software Development :: Libraries :: Python Modules
Classifier: Topic :: Software Development :: Quality Assurance
Requires-Dist: confusables
Requires-Dist: cython
Requires-Dist: flake8 (>3.0.0)
